//  bytecode opcode, JVM v6.5

pub const NOP: u8 = 0x00;
pub const ACONST_NULL: u8 = 0x01;
pub const ICONST_M1: u8 = 0x02;
pub const ICONST_0: u8 = 0x03;
pub const ICONST_1: u8 = 0x04;
pub const ICONST_2: u8 = 0x05;
pub const ICONST_3: u8 = 0x06;
pub const ICONST_4: u8 = 0x07;
pub const ICONST_5: u8 = 0x08;
pub const LCONST_0: u8 = 0x09;
pub const BIPUSH: u8 = 0x10;
pub const SIPUSH: u8 = 0x11;
pub const LDC: u8 = 0x12;
pub const ILOAD: u8 = 0x15;
pub const ALOAD: u8 = 0x19;
pub const ILOAD_0: u8 = 0x1a;
pub const ILOAD_1: u8 = 0x1b;
pub const ILOAD_2: u8 = 0x1c;
pub const ILOAD_3: u8 = 0x1d;
pub const ALOAD_0: u8 = 0x2a;
pub const ALOAD_1: u8 = 0x2b;
pub const ALOAD_2: u8 = 0x2c;
pub const ALOAD_3: u8 = 0x2d;
pub const ISTORE: u8 = 0x36;
pub const ASTORE: u8 = 0x3a;
pub const ISTORE_0: u8 = 0x3b;
pub const ISTORE_1: u8 = 0x3c;
pub const ISTORE_2: u8 = 0x3d;
pub const ISTORE_3: u8 = 0x3e;
pub const ASTORE_0: u8 = 0x4b;
pub const ASTORE_1: u8 = 0x4c;
pub const ASTORE_2: u8 = 0x4d;
pub const ASTORE_3: u8 = 0x4e;
pub const POP: u8 = 0x57;
pub const DUP: u8 = 0x59;
pub const IADD: u8 = 0x60;
pub const ISUB: u8 = 0x64;
pub const IMUL: u8 = 0x68;
pub const IDIV: u8 = 0x6c;
pub const IREM: u8 = 0x70;
pub const INEG: u8 = 0x74;
pub const IINC: u8 = 0x84;
pub const IFEQ: u8 = 0x99;
pub const IFNE: u8 = 0x9a;
pub const IFLT: u8 = 0x9b;
pub const IFGE: u8 = 0x9c;
pub const IFGT: u8 = 0x9d;
pub const IFLE: u8 = 0x9e;
pub const IF_ICMPEQ: u8 = 0x9f;
pub const IF_ICMPNE: u8 = 0xa0;
pub const IF_ICMPLT: u8 = 0xa1;
pub const IF_ICMPGE: u8 = 0xa2;
pub const IF_ICMPGT: u8 = 0xa3;
pub const IF_ICMPLE: u8 = 0xa4;
pub const GOTO: u8 = 0xa7;
pub const IRETURN: u8 = 0xac;
pub const ARETURN: u8 = 0xb0;
pub const RETURN: u8 = 0xb1;
pub const GETSTATIC: u8 = 0xb2;
pub const PUTSTATIC: u8 = 0xb3;
pub const GETFIELD: u8 = 0xb4;
pub const PUTFIELD: u8 = 0xb5;
pub const INVOKEVIRTUAL: u8 = 0xb6;
pub const INVOKESPECIAL: u8 = 0xb7;
pub const INVOKESTATIC: u8 = 0xb8;
pub const NEW: u8 = 0xbb;
pub const ARRAYLENGTH: u8 = 0xbe;
pub const ATHROW: u8 = 0xbf;
pub const INSTANCEOF: u8 = 0xc1;
pub const IFNULL: u8 = 0xc6;
pub const IFNONNULL: u8 = 0xc7;
